attipy/__about__.py
attipy/__init__.py
attipy/_ahrs.py
attipy/_attitude.py
attipy/_kalman.py
attipy/_quatops.py
attipy/_simulate.py
attipy/_statespace.py
attipy/_transforms.py
attipy/_vectorops.py
attipy-0.0.7.dist-info/METADATA
attipy-0.0.7.dist-info/WHEEL
attipy-0.0.7.dist-info/licenses/LICENSE
attipy-0.0.7.dist-info/RECORD
