Metadata-Version: 2.4
Name: attipy
Version: 0.0.7
Summary: A Python library for attitude estimation using inertial measurement units (IMUs)
Project-URL: Homepage, https://github.com/vegardrsolum/attipy
Project-URL: Issues, https://github.com/vegardrsolum/attipy/issues
Author-email: "Vegard R. Solum" <vegard.rorvik.solum@gmail.com>
License-File: LICENSE
Classifier: License :: OSI Approved :: MIT License
Classifier: Operating System :: OS Independent
Classifier: Programming Language :: Python :: 3.10
Classifier: Programming Language :: Python :: 3.11
Requires-Python: >=3.10
Requires-Dist: numba
Requires-Dist: numpy
Requires-Dist: scipy
